{
  "keyword": "Receiver",
  "timestamp": "2026-05-03 00:07:15",
  "related_queries": {
    "top": [
      {
        "query": "bluetooth",
        "value": 100
      },
      {
        "query": "bluetooth receiver",
        "value": 98
      },
      {
        "query": "wireless receiver",
        "value": 98
      },
      {
        "query": "stereo receiver",
        "value": 86
      },
      {
        "query": "audio receiver",
        "value": 56
      },
      {
        "query": "av receiver",
        "value": 51
      },
      {
        "query": "usb receiver",
        "value": 45
      },
      {
        "query": "sony receiver",
        "value": 39
      },
      {
        "query": "wide receiver",
        "value": 38
      },
      {
        "query": "receiver hitch",
        "value": 36
      },
      {
        "query": "tv receiver",
        "value": 35
      },
      {
        "query": "bluetooth audio receiver",
        "value": 32
      },
      {
        "query": "air receiver",
        "value": 32
      },
      {
        "query": "receiver yamaha",
        "value": 20
      },
      {
        "query": "transmitter and receiver",
        "value": 18
      },
      {
        "query": "phone receiver",
        "value": 17
      },
      {
        "query": "denon receiver",
        "value": 17
      },
      {
        "query": "denon",
        "value": 17
      },
      {
        "query": "logitech",
        "value": 16
      },
      {
        "query": "pioneer receiver",
        "value": 15
      },
      {
        "query": "home theater receiver",
        "value": 13
      },
      {
        "query": "lower receiver",
        "value": 13
      },
      {
        "query": "onkyo receiver",
        "value": 12
      },
      {
        "query": "sky receiver",
        "value": 11
      },
      {
        "query": "upper receiver",
        "value": 11
      }
    ],
    "rising": [
      {
        "query": "joe burrow receiver chemistry building",
        "value": 4250
      },
      {
        "query": "former georgia receiver nfl comeback",
        "value": 2300
      },
      {
        "query": "老虎",
        "value": 300
      },
      {
        "query": "blemished 80 lower receiver for sale",
        "value": 160
      },
      {
        "query": "vz61 receiver",
        "value": 90
      }
    ]
  }
}